flet_cacheimg/__init__.py
flet_cacheimg/flet_cacheimg.py
flutter/flet_cacheimg/CHANGELOG.md
flutter/flet_cacheimg/LICENSE
flutter/flet_cacheimg/README.md
flutter/flet_cacheimg/pubspec.lock
flutter/flet_cacheimg/pubspec.yaml
flutter/flet_cacheimg/lib/flet_cacheimg.dart
flutter/flet_cacheimg/lib/src/create_control.dart
flutter/flet_cacheimg/lib/src/flet_cacheavatar.dart
flutter/flet_cacheimg/lib/src/flet_cacheimg.dart
flutter/flet_cacheimg/lib/src/text_preload_images.dart
flet_cacheimg-0.2.1.dist-info/METADATA
flet_cacheimg-0.2.1.dist-info/WHEEL
flet_cacheimg-0.2.1.dist-info/top_level.txt
flet_cacheimg-0.2.1.dist-info/RECORD
