Metadata-Version: 2.4
Name: flet-cacheimg
Version: 0.2.1
Summary: CacheImage and CacheCircleAvatar control for Flet.
Author-email: Flet contributors <you@example.com>
Project-URL: Homepage, https://github.com/ReYaNOW/flet-cacheimg
Project-URL: Documentation, https://github.com/ReYaNOW/flet-cacheimg
Project-URL: Repository, https://github.com/ReYaNOW/flet-cacheimg
Project-URL: Issues, https://github.com/ReYaNOW/flet-cacheimg/issues
Requires-Python: >=3.9
Requires-Dist: flet>=0.28.3
